{
  "generatedAt": "2026-06-08T13:45:00+12:00",
  "sessionLabel": "PRE-LONDON OPEN",
  "pair": "EUR/USD",
  "lean": {
    "direction": "BEARISH",
    "conviction": "MODERATE",
    "bull": 3,
    "bear": 8,
    "reasoning": "NFP strong beat + 93K revisions. 72K OI build (institutional short). VIX 21.5 (risk-off). 200 EMA now ceiling (114 pips above). Warsh hawkish regime. Iran-Israel missile exchange + Hormuz combat = war premium reasserting. Brent back above $95. All forces bearish EUR.",
    "catalyst": "Iran escalation overnight. CPI Thursday is the week's pivot — cool miss = 89% ride, hot = validates rate hike narrative."
  },
  "session": {
    "asianRange": 0,
    "asianHigh": 0,
    "asianLow": 0,
    "compression": 0,
    "bodyCoherence": 0,
    "dayOfWeek": "Monday",
    "dayRule": "Monday — 75% directional match. Best directional day.",
    "dayRuleStatus": "CLEAR"
  },
  "positioning": {
    "cotPercentile": 34,
    "cotDirection": "bearish",
    "riskReversal": -0.40,
    "rrPrev": -0.61,
    "rrTrend": "improving",
    "oiChange": 2.3,
    "divergence": false
  },
  "terrain": {
    "nextEvent": "2026-06-12T00:30:00+12:00",
    "nextEventName": "US CPI (Thu 12:30am NZT)",
    "hoursToEvent": null,
    "pinRisk": 1.1500,
    "pinDistance": 29,
    "pinStatus": "ACTIVE",
    "cleanAir": 38,
    "levelClusters": 1,
    "eventProtocol": "CPI cool miss = 89% directional. CPI hot = messy, stand aside."
  },
  "regime": {
    "chainActive": 4,
    "chainTotal": 13,
    "chainStatus": "ELEVATED"
  },
  "gates": [
    { "name": "Session",  "status": "waiting", "detail": "Asian range not yet formed — London open tonight" },
    { "name": "Convict",  "status": "clear",   "detail": "Bear 8 vs Bull 3 — strong bearish conviction" },
    { "name": "Terrain",  "status": "clear",   "detail": "1.1618 resistance above, clean air to 1.1480" },
    { "name": "Clear",    "status": "clear",   "detail": "CPI Thu 12:30am = 5.5h post-London — outside 4h window" },
    { "name": "Confirm",  "status": "waiting", "detail": "Awaiting London open" }
  ],
  "levels": [
    { "price": 1.1641, "label": "200 EMA", "type": "ema", "note": "Tom's platform (Jun 7) — CEILING" },
    { "price": 1.1618, "label": "Fib 61.8% — Resistance", "type": "fib" },
    { "price": 1.1600, "label": "Round Number", "type": "round" },
    { "price": 1.1529, "label": "◆ PRICE", "type": "current" },
    { "price": 1.1500, "label": "Round / Pin Risk", "type": "round" },
    { "price": 1.1480, "label": "S1 zone", "type": "pivot" },
    { "price": 1.1416, "label": "Fib swing low", "type": "fib" },
    { "price": 1.1400, "label": "Round Number", "type": "round" }
  ],
  "dangerZones": [
    { "type": "active", "icon": "🔴", "title": "IRAN-ISRAEL ESCALATION", "detail": "Four waves of Iranian missiles at Israel. Hormuz combat active — US struck radar sites, shot down 4 drones. War premium reasserting. Brent back above $95." },
    { "type": "active", "icon": "🔴", "title": "1.1500 PIN RISK — 29 pips", "detail": "Major round number. NY cut expiries likely clustered. Watch for gravitational pull." },
    { "type": "nearby", "icon": "⚡", "title": "US CPI — Thursday 12:30am NZT", "detail": "Cool miss = 89% directional ride. Hot/inline = messy. 5.5h post-London = outside Gate 3 window. Week's pivot event." },
    { "type": "nearby", "icon": "⚡", "title": "ECB Rate Decision — Friday 12:15am NZT", "detail": "Expected 2.40% (hike from 2.15%). ECB + PPI simultaneous = Friday session chaos." },
    { "type": "info", "icon": "ℹ️", "title": "OPEC-JMMC + OPEC Meetings", "detail": "Sunday-Monday. Any production response to Iran escalation moves oil further." }
  ],
  "bracket": {
    "active": false,
    "day": "Monday",
    "reason": "Not Wed/Thu — directional system",
    "eur": { "range": "25-40", "offset": "+5/-5", "tp": 35 },
    "gbp": { "range": "20-25", "offset": "+7/-7", "tp": 35 }
  }
}