{
  "generatedAt": "2026-06-12T18:31:13.370271+12:00",
  "sessionLabel": "PRE-LONDON OPEN",
  "pair": "EUR/USD",
  "lean": {
    "direction": "NEUTRAL",
    "conviction": "LOW",
    "bull": 6,
    "bear": 6,
    "reasoning": "Price 42 pips below 200 EMA. VIX elevated 19.4 (avg 17.6) \u2014 risk-off. DXY weakening \u2014 EUR tailwind. COT AM 13th %ile \u2014 institutional bearish. Iran / Hormuz / Oil Supply Risk.",
    "catalyst": ""
  },
  "session": {
    "asianRange": 26,
    "asianHigh": 1.15888,
    "asianLow": 1.1562,
    "compression": 0.667,
    "bodyCoherence": 0.599,
    "dayOfWeek": "Friday",
    "dayRule": "Friday \u2014 trade to structural level. Hard exit Saturday NZT.",
    "dayRuleStatus": "CLEAR"
  },
  "positioning": {
    "cotPercentile": 13,
    "cotDirection": "bearish",
    "riskReversal": -0.6,
    "rrPrev": -0.7,
    "rrTrend": "improving",
    "oiChange": 0.0,
    "divergence": false
  },
  "terrain": {
    "nextEvent": null,
    "nextEventName": "None",
    "hoursToEvent": null,
    "pinRisk": 1.155,
    "pinDistance": 20,
    "pinStatus": "ACTIVE",
    "cleanAir": 50,
    "levelClusters": 0,
    "eventProtocol": "No event protocol active."
  },
  "regime": {
    "chainActive": 3,
    "chainTotal": 13,
    "chainStatus": "ELEVATED"
  },
  "gates": [
    {
      "name": "Session",
      "status": "pending",
      "detail": "Range 26 pips \u2014 QUALIFIED \u2705 (75% clean break) \u00b7 Compression 66.7% standard session character \u00b7 Structure 60% MIXED \u2014 read wicks carefully"
    },
    {
      "name": "Convict",
      "status": "waiting",
      "detail": "COT AM 13th pct \u00b7 RR 1W -0.60 improving \u00b7 DXY weakening"
    },
    {
      "name": "Terrain",
      "status": "clear",
      "detail": "No obstruction flagged"
    },
    {
      "name": "Clear",
      "status": "clear",
      "detail": "No high-impact events this session"
    },
    {
      "name": "Confirm",
      "status": "waiting",
      "detail": "In 73 min \u2014 monitor Asian range + candle character"
    }
  ],
  "levels": [
    {
      "price": 1.1748,
      "label": "Fib 50%",
      "type": "fib"
    },
    {
      "price": 1.17,
      "label": "Round Number",
      "type": "round"
    },
    {
      "price": 1.16426,
      "label": "50 EMA Daily",
      "type": "ema"
    },
    {
      "price": 1.1613,
      "label": "200 EMA",
      "type": "ema",
      "note": "yfinance (~30 pip variance \u2014 use platform value) \u2014 CEILING"
    },
    {
      "price": 1.16,
      "label": "Round Number",
      "type": "round"
    },
    {
      "price": 1.15888,
      "label": "Asian High",
      "type": "asian"
    },
    {
      "price": 1.15701,
      "label": "\u25c6 PRICE",
      "type": "current"
    },
    {
      "price": 1.1562,
      "label": "Asian Low",
      "type": "asian"
    },
    {
      "price": 1.15576,
      "label": "Pivot R1",
      "type": "pivot"
    },
    {
      "price": 1.15141,
      "label": "Pivot S1",
      "type": "pivot"
    },
    {
      "price": 1.15,
      "label": "Round Number",
      "type": "round"
    },
    {
      "price": 1.1416,
      "label": "Fib swing low",
      "type": "fib"
    }
  ],
  "dangerZones": [
    {
      "type": "active",
      "icon": "\ud83d\udd34",
      "title": "1.1550 PIN RISK \u2014 20 pips",
      "detail": "Major round number. NY cut expiries likely clustered."
    }
  ],
  "bracket": {
    "active": false,
    "day": "Friday",
    "reason": "Not Wed/Thu \u2014 directional system",
    "eur": {
      "range": "25-40",
      "offset": "+5/-5",
      "tp": 35
    },
    "gbp": {
      "range": "20-25",
      "offset": "+7/-7",
      "tp": 35
    }
  }
}